motorcortex_python_tools-1.2.1.data/scripts/mcx-datalogger.py
motorcortex_python_tools-1.2.1.data/scripts/mcx-dataplot.py
motorcortex_python_tools-1.2.1.dist-info/DESCRIPTION.rst
motorcortex_python_tools-1.2.1.dist-info/METADATA
motorcortex_python_tools-1.2.1.dist-info/RECORD
motorcortex_python_tools-1.2.1.dist-info/WHEEL
motorcortex_python_tools-1.2.1.dist-info/metadata.json
motorcortex_python_tools-1.2.1.dist-info/top_level.txt
motorcortex_tools/__init__.py
motorcortex_tools/datalogger.py
